desktop_parser/__init__.py
desktop_parser/desktop.py
desktop_parser-0.1.1.dist-info/LICENSE
desktop_parser-0.1.1.dist-info/WHEEL
desktop_parser-0.1.1.dist-info/METADATA
desktop_parser-0.1.1.dist-info/RECORD
