Metadata-Version: 2.1
Name: desktop-parser
Version: 0.1.1
Summary: Parse .desktop files
Home-page: https://desktopcreatorteam.github.io/
License: GPL-3.0-or-later
Keywords: desktop,linux,freedesktop,parser,file,format,standard
Author: 0xMRTT
Author-email: 0xMRTT@tuta.io
Maintainer: 0xMRTT
Maintainer-email: 0xMRTT@tuta.io
Requires-Python: >=3.7,<4.0
Classifier: Development Status :: 3 - Alpha
Classifier: Environment :: Console
Classifier: Intended Audience :: Developers
Classifier: License :: OSI Approved :: GNU General Public License v3 or later (GPLv3+)
Classifier: Operating System :: POSIX :: Linux
Classifier: Programming Language :: Python
Classifier: Programming Language :: Python :: 3
Classifier: Programming Language :: Python :: 3.7
Classifier: Programming Language :: Python :: 3.8
Classifier: Programming Language :: Python :: 3.9
Classifier: Programming Language :: Python :: 3.10
Classifier: Topic :: Software Development :: Libraries :: Python Modules
Classifier: Topic :: Utilities
Project-URL: Bug Tracker, https://github.com/DesktopCreatorTeam/DesktopCreator/issues
Project-URL: Documentation, https://desktopcreatorteam.github.io/
Project-URL: Repository, https://github.com/DesktopCreatorTeam/DesktopCreator
